batnotifsd/__init__.py
batnotifsd/batnotifsd.py
batnotifsd-1.0.5.dist-info/METADATA
batnotifsd-1.0.5.dist-info/WHEEL
batnotifsd-1.0.5.dist-info/licenses/LICENSE
batnotifsd-1.0.5.dist-info/RECORD
