Metadata-Version: 2.3
Name: batnotifsd
Version: 1.0.5
Summary: A Python script that sends notifications about the battery's status.
Project-URL: Homepage, https://github.com/Andy3153/batnotifsd
Project-URL: Issues, https://github.com/Andy3153/batnotifsd/issues
Author-email: Andrei Dobrete <andy3153@protonmail.com>
License-File: LICENSE
Classifier: Development Status :: 5 - Production/Stable
Classifier: Environment :: No Input/Output (Daemon)
Classifier: Environment :: X11 Applications
Classifier: Intended Audience :: End Users/Desktop
Classifier: License :: OSI Approved :: GNU General Public License v2 (GPLv2)
Classifier: Natural Language :: English
Classifier: Operating System :: POSIX :: Linux
Classifier: Programming Language :: Python :: 3.12
Classifier: Topic :: Desktop Environment :: Window Managers
Classifier: Topic :: System :: Monitoring
Classifier: Topic :: Utilities
Requires-Python: >=3.12
Requires-Dist: pydbus>=0.6.0
Requires-Dist: pygobject>=3.48.2
